usdm3_excel/__info__.py
usdm3_excel/__init__.py
usdm3_excel/__version__.py
usdm3_excel/export/__init__.py
usdm3_excel/export/study_content_sheet/__init__.py
usdm3_excel/export/study_content_sheet/content_panel.py
usdm3_excel/export/study_content_sheet/study_content_sheet.py
usdm3_excel/export/study_design_sheet/__init__.py
usdm3_excel/export/study_design_sheet/high_level_design_panel.py
usdm3_excel/export/study_design_sheet/main_panel.py
usdm3_excel/export/study_design_sheet/study_design_sheet.py
usdm3_excel/export/study_identifiers_sheet/__init__.py
usdm3_excel/export/study_identifiers_sheet/identifiers_panel.py
usdm3_excel/export/study_identifiers_sheet/study_identifiers_sheet.py
usdm3_excel/export/study_population_sheet/__init__.py
usdm3_excel/export/study_population_sheet/study_population_panel.py
usdm3_excel/export/study_population_sheet/study_population_sheet.py
usdm3_excel/export/study_sheet/__init__.py
usdm3_excel/export/study_sheet/dates_panel.py
usdm3_excel/export/study_sheet/main_panel.py
usdm3_excel/export/study_sheet/study_sheet.py
usdm3_excel/export/study_timeline_sheet/__init__.py
usdm3_excel/export/study_timeline_sheet/activities_panel.py
usdm3_excel/export/study_timeline_sheet/headings_panel.py
usdm3_excel/export/study_timeline_sheet/main_panel.py
usdm3_excel/export/study_timeline_sheet/study_timeline_sheet.py
usdm3_excel/export/study_timing_sheet/__init__.py
usdm3_excel/export/study_timing_sheet/study_timing_sheet.py
usdm3_excel/export/study_timing_sheet/timing_panel.py
usdm3_excel-0.2.1.dist-info/licenses/LICENSE
usdm3_excel-0.2.1.dist-info/METADATA
usdm3_excel-0.2.1.dist-info/WHEEL
usdm3_excel-0.2.1.dist-info/top_level.txt
usdm3_excel-0.2.1.dist-info/RECORD
